{
  "entries": [
    {
      "id": 2,
      "date": "",
      "topics": "sadfsdf",
      "entry": "oh come on now",
      "moodId": 4,
      "instructorId": 2
    },
    {
      "date": "2020-08-13",
      "topics": "um matt?",
      "entry": "its working ",
      "moodId": 4,
      "instructorId": 1,
      "id": 3
    },
    {
      "date": "2020-08-05",
      "topics": "dorernn",
      "entry": "dannerrgy",
      "moodId": 1,
      "instructorId": 1,
      "id": 60
    },
    {
      "date": "2020-08-20",
      "topics": "mhmm",
      "entry": "test for NO new tags but YES new ETS for NEWWW entry",
      "moodId": 2,
      "instructorId": 1,
      "id": 61
    },
    {
      "date": "2020-08-19",
      "topics": "moredart",
      "entry": "merryst",
      "moodId": 1,
      "instructorId": 1,
      "id": 62
    },
    {
      "date": "2020-08-13",
      "topics": "pass grabe",
      "entry": "c'est pat graveee sill ne marche pas ",
      "moodId": 4,
      "instructorId": 3,
      "id": 63
    },
    {
      "date": "2020-08-12",
      "topics": "caexist?",
      "entry": "oui je croie bein",
      "moodId": 3,
      "instructorId": 2,
      "id": 64
    },
    {
      "date": "2020-08-12",
      "topics": "anothuaa",
      "entry": "test for ET creation w/ existing tag",
      "moodId": 4,
      "instructorId": 1,
      "id": 65
    },
    {
      "date": "2020-08-12",
      "topics": "gmmm",
      "entry": "shouldd",
      "moodId": 3,
      "instructorId": 3,
      "id": 66
    },
    {
      "date": "2020-08-11",
      "topics": "tress",
      "entry": "noppee",
      "moodId": 2,
      "instructorId": 1,
      "id": 67
    },
    {
      "date": "2020-08-06",
      "topics": "nah",
      "entry": "shouldy",
      "moodId": 1,
      "instructorId": 2,
      "id": 68
    },
    {
      "date": "2020-08-20",
      "topics": "ddd",
      "entry": "nooo",
      "moodId": 1,
      "instructorId": 3,
      "id": 69
    },
    {
      "date": "2020-08-20",
      "topics": "sadfsdf",
      "entry": "mah",
      "moodId": 4,
      "instructorId": 1,
      "id": 70
    },
    {
      "date": "2020-08-19",
      "topics": "UGH",
      "entry": "is it json thing hm?",
      "moodId": 2,
      "instructorId": 1,
      "id": 71
    },
    {
      "date": "2020-08-18",
      "topics": "zing",
      "entry": "bahhhzinga",
      "moodId": 1,
      "instructorId": 2,
      "id": 72
    },
    {
      "date": "2020-08-20",
      "topics": "ahdang",
      "entry": "hmmyeah",
      "moodId": 4,
      "instructorId": 3,
      "id": 73
    },
    {
      "date": "2020-08-11",
      "topics": "Some shit",
      "entry": "more dangg",
      "moodId": 3,
      "instructorId": 1,
      "id": 74
    },
    {
      "date": "2020-08-13",
      "topics": "Some wetness",
      "entry": "nastyness",
      "moodId": 1,
      "instructorId": 3,
      "id": 75
    },
    {
      "date": "2020-08-23",
      "topics": "last attempt",
      "entry": "before goodnitey",
      "moodId": 3,
      "instructorId": 1,
      "id": 76
    },
    {
      "date": "2020-08-12",
      "topics": "onemixer",
      "entry": "somemixx",
      "moodId": 4,
      "instructorId": 2,
      "id": 77
    }
  ],
  "moods": [
    {
      "id": 1,
      "label": "overwhelmed"
    },
    {
      "id": 2,
      "label": "grokking"
    },
    {
      "id": 3,
      "label": "confused"
    },
    {
      "id": 4,
      "label": "excited"
    }
  ],
  "instructors": [
    {
      "id": 1,
      "first_name": "Steve",
      "last_name": "Brownsauce",
      "expertise": "Querying your mom"
    },
    {
      "id": 2,
      "first_name": "Kristin",
      "last_name": "McDownToBusiness",
      "expertise": "Tellin' it like it is"
    },
    {
      "id": 3,
      "first_name": "Jamestown",
      "last_name": "Hardlyknewya",
      "expertise": "peacin' the EFF OUT"
    }
  ],
  "tags": [
    {
      "subject": "should",
      "id": 14
    },
    {
      "subject": "camarches",
      "id": 68
    },
    {
      "subject": "tresbien",
      "id": 69
    },
    {
      "subject": "camaros",
      "id": 70
    },
    {
      "subject": "wet",
      "id": 71
    },
    {
      "subject": "wetsauce",
      "id": 72
    },
    {
      "subject": "sammy",
      "id": 73
    },
    {
      "subject": "nasty",
      "id": 74
    },
    {
      "subject": "brownsauce",
      "id": 75
    },
    {
      "subject": "wetness",
      "id": 76
    },
    {
      "subject": "lets",
      "id": 77
    },
    {
      "subject": "try",
      "id": 78
    },
    {
      "subject": "somealott",
      "id": 79
    },
    {
      "subject": "moretoend",
      "id": 80
    },
    {
      "subject": "truth",
      "id": 81
    }
  ],
  "entriesTags": [
    {
      "id": 1,
      "entryId": 3,
      "tagId": 14
    },
    {
      "id": 2,
      "entryId": 2,
      "tagId": 14
    },
    {
      "entryId": 71,
      "tagId": 14,
      "id": 3
    },
    {
      "entryId": 73,
      "tagId": 14,
      "id": 4
    },
    {
      "entryId": 73,
      "tagId": 71,
      "id": 5
    },
    {
      "entryId": 75,
      "tagId": 74,
      "id": 6
    },
    {
      "entryId": 75,
      "tagId": 75,
      "id": 7
    },
    {
      "entryId": 75,
      "tagId": 76,
      "id": 8
    },
    {
      "entryId": 75,
      "tagId": 74,
      "id": 9
    },
    {
      "entryId": 75,
      "tagId": 75,
      "id": 10
    },
    {
      "entryId": 75,
      "tagId": 76,
      "id": 11
    },
    {
      "entryId": 76,
      "tagId": 77,
      "id": 12
    },
    {
      "entryId": 76,
      "tagId": 78,
      "id": 13
    },
    {
      "entryId": 76,
      "tagId": 79,
      "id": 14
    },
    {
      "entryId": 76,
      "tagId": 80,
      "id": 15
    }
  ]
}